{
  "driver_ratings": [
    "fromSchool",
    "targetId",
    "review",
    "historyId",
    "rating",
    "timestamp"
  ],
  "drivers": [
    "photoSKCK",
    "statusShift",
    "slaScore",
    "rating",
    "photoSIM",
    "nik",
    "createdAt",
    "carryingCapacity",
    "averageRating",
    "workingHours",
    "email",
    "vehicleType",
    "currentIssueType",
    "address",
    "photoSTNK",
    "photoVehicle",
    "isGpsConsent",
    "vehiclePlate",
    "statusDelivery",
    "driverId",
    "name",
    "coverageArea",
    "isApproved",
    "profilephoto",
    "assignedVendorEmail",
    "currentNavigatingSchool",
    "phone",
    "lastUpdate",
    "statusHandover",
    "currentIssuePhoto",
    "vendorActionStatus",
    "currentIssueMsg",
    "currentLat",
    "currentLng"
  ],
  "governments": [
    "email",
    "name",
    "role"
  ],
  "schools": [
    "validasi_institusi",
    "address",
    "level",
    "latitude",
    "pic",
    "nip",
    "operasional",
    "schoolId",
    "porsi",
    "name",
    "email",
    "status",
    "longitude",
    "isApproved",
    "count_grade_1_3",
    "lastStudentCount",
    "lastUpdate",
    "count_grade_4_6",
    "assignedVendorEmail",
    "assignedDriverId",
    "picPosition",
    "photoFotoSekolah",
    "picName",
    "photoSK",
    "createdAt",
    "p13",
    "photoSuratAktif",
    "dropOffPoint",
    "photoStempel",
    "npsn",
    "activeDays",
    "pSMP",
    "p46",
    "breakTime",
    "phone",
    "schoolStart",
    "location",
    "picPhone",
    "porsiSMP_SMA",
    "porsiSD13",
    "porsiSD46",
    "schoolName"
  ],
  "users": [
    "uid",
    "createdAt",
    "role",
    "isApproved",
    "email"
  ],
  "vendor_ratings": [
    "fromSchool",
    "targetId",
    "review",
    "historyId",
    "rating",
    "timestamp"
  ],
  "vendors": [
    "vendorId",
    "email",
    "safetyVerified",
    "safetyTemp",
    "safetyConfirmed",
    "isManualSubmit",
    "location",
    "name",
    "aiVerified",
    "menuPhotoBase64",
    "targetPorsi",
    "complianceScore",
    "averageRating",
    "totalCapital",
    "rawMaterialWeight",
    "cookingStartTime",
    "cookedCount",
    "cookingEndTime",
    "chillerTemp",
    "safetyVerifiedAt",
    "samplePhotoUrl",
    "currentStep",
    "statusProduksi",
    "photoHygiene",
    "photoIzinOps",
    "nib",
    "latitude",
    "employeeCount",
    "ownerName",
    "hasHalal",
    "photoHalal",
    "longitude",
    "photoPIRT",
    "address",
    "photoDapur",
    "npwp",
    "setujuSLA",
    "operatingHours",
    "lastUpdate",
    "setujuLaporan",
    "menuTypes",
    "setujuGizi",
    "isApproved"
  ]
}